Metadata-Version: 1.1
Name: camel-snake-pep8
Version: 0.2.2
Summary: Use Python-Rope to convert names in a Python project to conform with PEP-8.
Home-page: https://github.com/abarker/camel-snake-pep8
Author: Allen Barker
Author-email: Allen.L.Barker@gmail.com
License: MIT
Keywords: pep-8,PEP-8,PEP8,refactor,rename
Platform: UNKNOWN
Classifier: Development Status :: 5 - Production/Stable
Classifier: Intended Audience :: Developers
Classifier: License :: OSI Approved :: MIT License
Classifier: Operating System :: Unix
Classifier: Operating System :: POSIX
Classifier: Operating System :: Microsoft :: Windows
Classifier: Programming Language :: Python
Classifier: Programming Language :: Python :: 2.7
Classifier: Programming Language :: Python :: 3
Classifier: Programming Language :: Python :: 3.4
Classifier: Programming Language :: Python :: 3.5
Classifier: Programming Language :: Python :: 3.6
Classifier: Programming Language :: Python :: 3.7
Classifier: Programming Language :: Python :: 3.8
Classifier: Programming Language :: Python :: Implementation :: CPython
Classifier: Programming Language :: Python :: Implementation :: PyPy
Classifier: Topic :: Utilities
